brainframe_onvif_tools/.config.csv.swp
brainframe_onvif_tools/__init__.py
brainframe_onvif_tools/brainframe-onvif-tools.py
brainframe_onvif_tools/camera_onvif_info.json
brainframe_onvif_tools/cli.py
brainframe_onvif_tools/command_utils.py
brainframe_onvif_tools/config.csv
brainframe_onvif_tools/credentials.txt
brainframe_onvif_tools/discover_onvif_cameras.py
brainframe_onvif_tools/get_camera_onvif_info.py
brainframe_onvif_tools/print_utils.py
brainframe_onvif_tools/scan_onvif_cameras.py
brainframe_onvif_tools/take_snapshot.py
brainframe_onvif_tools/translations/portal.en.yml
brainframe_onvif_tools/validate_onvif_cameras.py
brainframe_onvif_tools-0.5.3.dist-info/METADATA
brainframe_onvif_tools-0.5.3.dist-info/WHEEL
brainframe_onvif_tools-0.5.3.dist-info/entry_points.txt
brainframe_onvif_tools-0.5.3.dist-info/RECORD
