Metadata-Version: 2.1
Name: brainframe-onvif-tools
Version: 0.5.3
Summary: Python CLI tools for discovering, scanning, and validating ONVIF cameras.
License: BSD License
Author: Stephen Li
Author-email: stephen@aotu.ai
Requires-Python: >=3.9,<4.0
Classifier: License :: OSI Approved :: BSD License
Classifier: License :: Other/Proprietary License
Classifier: Programming Language :: Python :: 3
Classifier: Programming Language :: Python :: 3.9
Classifier: Programming Language :: Python :: 3.10
Classifier: Programming Language :: Python :: 3.11
Classifier: Programming Language :: Python :: 3.12
Requires-Dist: PyYAML (>=6.0.2,<7.0.0)
Requires-Dist: netifaces (>=0.11.0)
Requires-Dist: onvif-zeep (>=0.2.12)
Requires-Dist: python-i18n (>=0.3.9,<0.4.0)
Requires-Dist: requests (>=2.31.0)
Requires-Dist: wsdiscovery (>=2.0.0)
Requires-Dist: zeep (>=4.2.1)
